strands_research_agent/__init__.py
strands_research_agent/agent.py
strands_research_agent/handlers/__init__.py
strands_research_agent/handlers/callback_handler.py
strands_research_agent/tools/__init__.py
strands_research_agent/tools/notify.py
strands_research_agent/tools/scraper.py
strands_research_agent/tools/store_in_kb.py
strands_research_agent/tools/system_prompt.py
strands_research_agent/tools/tasks.py
strands_research_agent/tools/use_github.py
strands_research_agent-0.1.5.dist-info/METADATA
strands_research_agent-0.1.5.dist-info/WHEEL
strands_research_agent-0.1.5.dist-info/entry_points.txt
strands_research_agent-0.1.5.dist-info/RECORD
