Metadata-Version: 2.4
Name: strands-research-agent
Version: 0.1.5
Summary: Sample Research Agent powered by Strands Agents SDK
Project-URL: Homepage, https://github.com/strands-agents/samples
Project-URL: Repository, https://github.com/strands-agents/samples
Project-URL: Issues, https://github.com/strands-agents/samples/issues
Project-URL: Documentation, https://strandsagents.com
Author-email: AWS <opensource@amazon.com>, Cagatay Cali <cagataycali@icloud.com>
License: MIT
Keywords: agent,ai,automation,aws,github,knowledge-base,research,strands,strands-agents
Classifier: Development Status :: 4 - Beta
Classifier: Intended Audience :: Developers
Classifier: Intended Audience :: Science/Research
Classifier: License :: OSI Approved :: MIT License
Classifier: Operating System :: OS Independent
Classifier: Programming Language :: Python :: 3
Classifier: Programming Language :: Python :: 3.10
Classifier: Programming Language :: Python :: 3.11
Classifier: Programming Language :: Python :: 3.12
Classifier: Programming Language :: Python :: 3.13
Classifier: Topic :: Scientific/Engineering :: Artificial Intelligence
Classifier: Topic :: Scientific/Engineering :: Information Analysis
Classifier: Topic :: Software Development :: Libraries :: Python Modules
Requires-Python: >=3.10
Requires-Dist: beautifulsoup4>=4.9.0
Requires-Dist: colorama>=0.4.0
Requires-Dist: halo
Requires-Dist: numpy
Requires-Dist: prompt-toolkit>=3.0.0
Requires-Dist: requests>=2.25.0
Requires-Dist: rich>=10.0.0
Requires-Dist: strands-agents-tools>=0.1.0
Requires-Dist: strands-agents>=1.0.0
Requires-Dist: strands-agents[otel]
Provides-Extra: all
Requires-Dist: strands-agents[anthropic]; extra == 'all'
Requires-Dist: strands-agents[litellm]; extra == 'all'
Requires-Dist: strands-agents[llamaapi]; extra == 'all'
Requires-Dist: strands-agents[mistral]; extra == 'all'
Requires-Dist: strands-agents[ollama]; extra == 'all'
Requires-Dist: strands-agents[openai]; extra == 'all'
Provides-Extra: anthropic
Requires-Dist: strands-agents[anthropic]; extra == 'anthropic'
Provides-Extra: binary
Requires-Dist: pyinstaller>=5.0; extra == 'binary'
Provides-Extra: dev
Requires-Dist: black>=22.0; extra == 'dev'
Requires-Dist: isort>=5.0; extra == 'dev'
Requires-Dist: mypy>=1.0; extra == 'dev'
Requires-Dist: pre-commit>=3.0; extra == 'dev'
Requires-Dist: pytest>=7.0; extra == 'dev'
Requires-Dist: ruff>=0.1.0; extra == 'dev'
Provides-Extra: litellm
Requires-Dist: strands-agents[litellm]; extra == 'litellm'
Provides-Extra: llamaapi
Requires-Dist: strands-agents[llamaapi]; extra == 'llamaapi'
Provides-Extra: mistral
Requires-Dist: strands-agents[mistral]; extra == 'mistral'
Provides-Extra: ollama
Requires-Dist: strands-agents[ollama]; extra == 'ollama'
Provides-Extra: openai
Requires-Dist: strands-agents[openai]; extra == 'openai'
